norminette/__init__.py
norminette/__main__.py
norminette/colors.py
norminette/context.py
norminette/errors.py
norminette/exceptions.py
norminette/file.py
norminette/lexer/__init__.py
norminette/lexer/dictionary.py
norminette/lexer/lexer.py
norminette/lexer/tokens.py
norminette/norm_error.py
norminette/registry.py
norminette/rules/__init__.py
norminette/rules/check_assignation.py
norminette/rules/check_assignation_indent.py
norminette/rules/check_block_start.py
norminette/rules/check_brace.py
norminette/rules/check_comment.py
norminette/rules/check_comment_line_len.py
norminette/rules/check_control_statement.py
norminette/rules/check_declaration.py
norminette/rules/check_empty_line.py
norminette/rules/check_enum_var_decl.py
norminette/rules/check_expression_statement.py
norminette/rules/check_func_arguments_name.py
norminette/rules/check_func_declaration.py
norminette/rules/check_func_spacing.py
norminette/rules/check_functions_count.py
norminette/rules/check_general_spacing.py
norminette/rules/check_global_naming.py
norminette/rules/check_header.py
norminette/rules/check_identifier_name.py
norminette/rules/check_in_header.py
norminette/rules/check_label.py
norminette/rules/check_line_count.py
norminette/rules/check_line_indent.py
norminette/rules/check_line_len.py
norminette/rules/check_many_instructions.py
norminette/rules/check_nest_line_indent.py
norminette/rules/check_newline_indent.py
norminette/rules/check_operators_spacing.py
norminette/rules/check_preprocessor_define.py
norminette/rules/check_preprocessor_include.py
norminette/rules/check_preprocessor_indent.py
norminette/rules/check_preprocessor_protection.py
norminette/rules/check_prototype_indent.py
norminette/rules/check_spacing.py
norminette/rules/check_struct_naming.py
norminette/rules/check_ternary.py
norminette/rules/check_utype_declaration.py
norminette/rules/check_variable_declaration.py
norminette/rules/check_variable_indent.py
norminette/rules/is_ambiguous_declaration.py
norminette-3.3.58.dist-info/LICENSE
norminette-3.3.58.dist-info/METADATA
norminette-3.3.58.dist-info/WHEEL
norminette-3.3.58.dist-info/entry_points.txt
norminette-3.3.58.dist-info/RECORD
