Metadata-Version: 2.3
Name: norminette
Version: 3.3.58
Summary: Open source C files linter for 42 Network campuses
License: MIT Licence
Keywords: 42,norminette
Author: 42
Author-email: pedago@42.fr
Requires-Python: >=3.8.1,<4.0.0
Classifier: Development Status :: 5 - Production/Stable
Classifier: Intended Audience :: Developers
Classifier: License :: OSI Approved :: MIT License
Classifier: License :: Other/Proprietary License
Classifier: Natural Language :: English
Classifier: Programming Language :: Python :: 3
Classifier: Programming Language :: Python :: 3.9
Classifier: Programming Language :: Python :: 3.10
Classifier: Programming Language :: Python :: 3.11
Classifier: Programming Language :: Python :: 3.12
Classifier: Programming Language :: Python :: 3.13
Classifier: Programming Language :: Python :: 3.8
Requires-Dist: argparse (>=1.4.0,<2.0.0)
Project-URL: Repository, https://github.com/42School/norminette
